{"name":"taudit_remediate_apply","title":"Apply remediations","description":"Apply low-risk remediations with backup + validation + auto-restore. Mutates pipeline files.","command":["remediate","--unstable","apply"],"args":{"paths":{"type":"path","required":true,"description":"Pipeline file(s) or directories to modify","flag":null,"position":1,"values":[],"default":null,"multiple":false,"must_exist":true,"within_workspace":true,"redact":false},"policy":{"type":"path","required":true,"description":"Policy path passed to `taudit verify` after rewrite","flag":"--policy","position":null,"values":[],"default":null,"multiple":false,"must_exist":true,"within_workspace":true,"redact":false},"format":{"type":"enum","required":false,"description":"Output format","flag":"--format","position":null,"values":["text","json"],"default":"json","multiple":false,"must_exist":false,"within_workspace":false,"redact":false},"allow_risky":{"type":"bool","required":false,"description":"Allow medium/high-risk transforms (off by default)","flag":"--allow-risky","position":null,"values":[],"default":null,"multiple":false,"must_exist":false,"within_workspace":false,"redact":false},"min_confidence":{"type":"number","required":false,"description":"Minimum confidence required for any transform to run","flag":"--min-confidence","position":null,"values":[],"default":null,"multiple":false,"must_exist":false,"within_workspace":false,"redact":false},"backup_root":{"type":"path","required":false,"description":"Override backup root","flag":"--backup-root","position":null,"values":[],"default":null,"multiple":false,"must_exist":false,"within_workspace":true,"redact":false}},"output":{"mode":"json","max_bytes":2097152,"expose_stderr":true},"policy":{"authority":"Mutate","read_only":false,"network":false,"writes_files":true,"approval":"always","requires_approval":false,"timeout_seconds":600},"env":{"inherit":false,"allow":[],"set":{}}}